fds/__init__.py
fds/sdk/__init__.py
fds/sdk/Publisher/__init__.py
fds/sdk/Publisher/api_client.py
fds/sdk/Publisher/configuration.py
fds/sdk/Publisher/exceptions.py
fds/sdk/Publisher/model_utils.py
fds/sdk/Publisher/rest.py
fds/sdk/Publisher/api/__init__.py
fds/sdk/Publisher/api/accounts_api.py
fds/sdk/Publisher/api/calculations_api.py
fds/sdk/Publisher/api/documents_api.py
fds/sdk/Publisher/apis/__init__.py
fds/sdk/Publisher/model/__init__.py
fds/sdk/Publisher/model/account_directories.py
fds/sdk/Publisher/model/calculation.py
fds/sdk/Publisher/model/calculation_status.py
fds/sdk/Publisher/model/calculation_status_summary.py
fds/sdk/Publisher/model/calculation_unit_status.py
fds/sdk/Publisher/model/document_directories.py
fds/sdk/Publisher/model/pa_calculation_column.py
fds/sdk/Publisher/model/pa_calculation_group.py
fds/sdk/Publisher/model/pa_calculation_parameters.py
fds/sdk/Publisher/model/pa_date_parameters.py
fds/sdk/Publisher/model/pa_identifier.py
fds/sdk/Publisher/model/pub_calculation_parameters.py
fds/sdk/Publisher/model/pub_date_parameters.py
fds/sdk/Publisher/model/pub_identifier.py
fds/sdk/Publisher/model/spar_calculation_parameters.py
fds/sdk/Publisher/model/spar_date_parameters.py
fds/sdk/Publisher/model/spar_identifier.py
fds/sdk/Publisher/model/vault_calculation_parameters.py
fds/sdk/Publisher/model/vault_date_parameters.py
fds/sdk/Publisher/model/vault_identifier.py
fds/sdk/Publisher/models/__init__.py
fds.sdk.Publisher-0.40.2.dist-info/LICENSE
fds.sdk.Publisher-0.40.2.dist-info/METADATA
fds.sdk.Publisher-0.40.2.dist-info/WHEEL
fds.sdk.Publisher-0.40.2.dist-info/top_level.txt
fds.sdk.Publisher-0.40.2.dist-info/RECORD
